maui_rc/__init__.py
maui_rc/datatypes.py
maui_rc/scope.py
maui_rc/subsystems/acquisition.py
maui_rc/subsystems/panelsetup.py
maui_rc/subsystems/wavedata.py
maui_rc/subsystems/waveform.py
maui_rc-0.1.4.dist-info/LICENSE
maui_rc-0.1.4.dist-info/METADATA
maui_rc-0.1.4.dist-info/WHEEL
maui_rc-0.1.4.dist-info/RECORD
